{"name":"vendor_lib_5a0315c4f26d922e4c75","content":{"../node_modules/process/browser.js":{"id":0,"meta":{}},"../node_modules/vue-resource/dist/vue-resource.es2015.js":{"id":1,"meta":{"harmonyModule":true},"exports":["default","Url","Http","Resource"]},"../node_modules/vue-router/dist/vue-router.esm.js":{"id":2,"meta":{"harmonyModule":true},"exports":["default"]},"../node_modules/vue/dist/vue.runtime.esm.js":{"id":3,"meta":{"harmonyModule":true},"exports":["default"]},"../node_modules/webpack/buildin/global.js":{"id":4,"meta":{}}}}